framework/__init__.py
framework/lib/__init__.py
framework/lib/libfuncs.py
framework/numfuncs/__init__.py
framework/numfuncs/num.py
framework/stringfuncs/__init__.py
framework/stringfuncs/str.py
gbdqa-0.1.0.dist-info/DESCRIPTION.rst
gbdqa-0.1.0.dist-info/METADATA
gbdqa-0.1.0.dist-info/RECORD
gbdqa-0.1.0.dist-info/WHEEL
gbdqa-0.1.0.dist-info/metadata.json
gbdqa-0.1.0.dist-info/top_level.txt
