Metadata-Version: 2.0
Name: gbdqa
Version: 0.1.0
Summary: Get even or odd
Home-page: UNKNOWN
Author: Rohan Amatya
Author-email: rohanneps@gmail.com
License: UNKNOWN
Keywords: Even Odd
Platform: UNKNOWN
